{
  "pmid": "41288624",
  "title": "Clinical characteristics, risk factor analysis, and outcomes of graft rejection after Descemet membrane endothelial keratoplasty.",
  "authors": [
    "Singh Shalini",
    "Ali Md Hasnat",
    "Chaurasia Sunita"
  ],
  "journal": "Indian journal of ophthalmology",
  "year": "2025",
  "abstract": "To report the clinical characteristics, risk factors, and outcomes of graft rejection after Descemet membrane endothelial keratoplasty (DMEK). Of the total of 1026 eyes of 935 patients that underwent DMEK, 25 eyes of 25 patients had rejection. The risk factors in 25 eyes were compared with those of control eyes without rejection during the same study period. The control group consisted of 98 eyes of 98 patients, who underwent DMEK during the same period and had no episode of rejection at a minimum and regular follow-up period of 2 years from the time of surgery. Overall, the incidence of rejection was 2.5%. The median age of patients was 53 (interquartile range, IQR, 45-62) years. In the control group, the median age was 65.5 (IQR 56.2-70.8) years. Most (88%) rejection episodes occurred within the first 2 years of surgery. Multivariate analysis showed younger age at surgery, male gender, rebubbling, cessation of topical steroids, and indication of DMEK (failed graft, corneal edema post-cataract surgery, and corneal edema due to inflammatory causes) as significant risk factors for graft rejection. No significant temporal correlation was observed with COVID-19 vaccination in the majority (92%). The mean endothelial cell loss following rejection was 72.5%. Kaplan-Meier survival plot showed the probability of graft survival was 90% at 1 year, 82% at 2 years, 80% at 3 years, 80% at 4 years, and 78% at 5-8 years. Our study suggests that the risk of rejection is higher for indications such as failed previous graft, post-cataract surgery edema, and edema postinflammatory causes, when compared to Fuchs endothelial dystrophy. Topical steroids should be continued at least up to 2 years after surgery as this is the most common time frame of the rejection episode. The majority (68%) of the rejection episodes were reversible and resulted in a favorable outcome.",
  "publication_types": [
    "Journal Article"
  ],
  "full_text": "Clinical characteristics, risk factor analysis, and outcomes of graft rejection after Descemet membrane endothelial keratoplasty\n\nPurpose:\n\nTo report the clinical characteristics, risk factors, and outcomes of graft rejection after Descemet membrane endothelial keratoplasty (DMEK).\n\nMethods:\n\nOf the total of 1026 eyes of 935 patients that underwent DMEK, 25 eyes of 25 patients had rejection. The risk factors in 25 eyes were compared with those of control eyes without rejection during the same study period. The control group consisted of 98 eyes of 98 patients, who underwent DMEK during the same period and had no episode of rejection at a minimum and regular follow-up period of 2 years from the time of surgery.\n\nResults:\n\nOverall, the incidence of rejection was 2.5%. The median age of patients was 53 (interquartile range, IQR, 45\u201362) years. In the control group, the median age was 65.5 (IQR 56.2\u201370.8) years. Most (88%) rejection episodes occurred within the first 2 years of surgery. Multivariate analysis showed younger age at surgery, male gender, rebubbling, cessation of topical steroids, and indication of DMEK (failed graft, corneal edema post-cataract surgery, and corneal edema due to inflammatory causes) as significant risk factors for graft rejection. No significant temporal correlation was observed with COVID-19 vaccination in the majority (92%). The mean endothelial cell loss following rejection was 72.5%. Kaplan\u2013Meier survival plot showed the probability of graft survival was 90% at 1 year, 82% at 2 years, 80% at 3 years, 80% at 4 years, and 78% at 5\u20138 years.\n\nConclusion:\n\nOur study suggests that the risk of rejection is higher for indications such as failed previous graft, post-cataract surgery edema, and edema postinflammatory causes, when compared to Fuchs endothelial dystrophy. Topical steroids should be continued at least up to 2 years after surgery as this is the most common time frame of the rejection episode. The majority (68%) of the rejection episodes were reversible and resulted in a favorable outcome.\n\nDescemet stripping endothelial keratoplasty (DSEK) and Descemet endothelial keratoplasty (DMEK) are the two popular techniques of endothelial keratoplasty (EK). One of the many reasons for the rapid adoption of the EK techniques was due to the lowered risk of rejection when compared to penetrating keratoplasty (PK).\n\nSome of the risk factors that have been identified for graft rejection in EK include young age, previous keratoplasty, corneal vascularization, coexisting glaucoma, sudden discontinuation of topical steroids, systemic comorbidities, peripheral anterior synechiae, and African American ancestry. The risk of rejection after DMEK is believed to be lower than that after DSEK. The rate of rejection after DMEK is variably reported, with a mean rate of 1.9% and a range of 0\u20136%. This broad range is attributed to several reasons such as divergence in ethnicity, indications of the DMEK, differences in the postoperative steroid regimen, variable period of follow-up after surgery, and sample sizes. Anshu et al. reported a rejection rate of <1% with a median follow-up of 13 months. Hos et al. reported a risk of 0.9% after 1 year and 2.3% after 2 and 4 years. Birbal et al. reported 5-year outcomes of 500 DMEK and a graft rejection rate of 2.8%. Basak et al. reported a rejection rate of 1.2%, with a median follow-up of 17 months.\n\nIn the present study, we report the demographics, clinical profile, and risk factors of graft rejection after DMEK performed at a tertiary care institution.\n\nMethods\n\nDuring the study period between January 2017 and March 2024, a total of 1026 eyes of 935 patients had undergone DMEK, of which 25 eyes of 25 patients were diagnosed with allograft rejection after DMEK. The analysis of 25 eyes with rejection episode was conducted retrospectively and was compared with a control group that comprised 98 eyes of 98 patients, who underwent DMEK during the same period and had no episode of rejection at a minimum and regular follow-up period of 2 years from the time of surgery. Data captured included demographic details, indication for DMEK, associated ocular comorbidities, clinical presentations of graft rejection, recovery of graft clarity, and endothelial cell loss after rejection episode in those eyes where graft clarity was restored following rejection episode. We also collected data related to COVID-19 vaccination in the study and the control group. Overall, out of 123 patients, 25 patients had a history of COVID-19 vaccination.\n\nOf the 1026 eyes that had DMEK, 45 eyes of 45 (4.38%) patients had primary graft failure and these were excluded from the analysis of rejection rate. The exact cause of primary graft failure could not be discerned and most likely was attributed to multitude factors such as complexity associated with the indication of surgery, iatrogenic causes, and donor-related factors.\n\nDMEK was performed by a team of experienced corneal surgeons and trained senior corneal fellows using DMEK scroll prepared by the surgeon in the operating room until 2022 and thereafter using prestripped DM scroll with a stromal window, received from the institute affiliated eye bank. The surgery was performed under peribulbar anesthesia. The patients were treated with topical broad-spectrum antibiotic four times daily for 1\u20132 weeks, prednisolone acetate 1% eyedrops (Pred Forte, Allergan) in weekly tapering dosage. Typically, the patients received topical steroids 6\u20138 times daily, which was tapered weekly to a maintenance dose of twice daily for 6 months, once daily till 2 years. In eyes with a steroid response, loteprednol etabonate 1% was advised after 1 year. Additional treatment with antiglaucoma medications was considered as in eyes with steroid response or patients with pre-existing or secondary glaucoma. In general, the protocol for follow-up after DMEK was day 1, day 3, 1 week, 4\u20136 weeks, 3\u20136 months, and 6 monthly thereafter for 2 years and yearly thereafter. In the eyes with significant graft detachments, rebubbling was performed with 100% air injection. At each visit, visual acuity, slit-lamp examination, and intraocular pressure (IOP) were documented. Specular microscopy was performed whenever possible.\n\nPrimary graft failure referred to the grafts where the corneal clarity failed to improve even at 6\u20138 weeks from surgery.\n\nThe definitions of graft rejection and graft failure are described as below:\n\nGraft Rejection: The graft rejection was diagnosed based on the previously described clinical features such as a decrease in visual acuity with evidence of edema in a previously clear and compact cornea with/without additional signs and symptoms such as keratic precipitates, anterior chamber inflammation, ocular congestion, pain, discomfort, and photophobia.\n\nGraft Failure: Graft failure was diagnosed when there was no improvement in corneal clarity for 3 months from the time of diagnosis of rejection.\n\nGraft rejections were treated with topical prednisolone acetate 1% in an hourly dosage for 4\u20136 days, followed by two hourly dosages for next 4\u20136 days, with a weekly tapering dosage to a maintenance dose of twice daily till 6 months and once a day thereafter. In those with severe rejection episodes (defined clinically as diffuse severe corneal edema), and with a short duration of history (<3 days), systemic steroid intravenous methyl prednisolone acetate 500 mg\u20131 g single dose was also given additionally.\n\nThe various parameters that were studied as potential risk factors for rejection were recipient\u2019s age, recipient\u2019s gender, donor\u2019s age, donor\u2019s gender, nonusage of steroids prior to rejection episode, indication of surgery, peripheral anterior synechiae, glaucoma, and rebubbling. Comparison of these parameters was done with the 98 eyes that had DMEK within the study period without the rejection episode.\n\nThe clinical characteristics of eyes with a successful reversal of graft clarity following rejection were compared with the eyes with persistent graft edema and failure after rejection. The various parameters studied were recipient\u2019s age and gender, concomitant procedure with DMEK, glaucoma, rebubbling, duration of rejection at the time of presentation in clinic, nonuse of steroids at initial presentation, donor\u2019s endothelial cell density (ECD), and age.\n\nStatistical analysis was performed using Statistical software R: a language and environment for statistical computing, Vienna, Austria. The presentation of the categorical variables was done in the form of number and percentage (%). The quantitative data were presented as the means \u00b1 SD and median with 25th and 75th percentiles (interquartile range). For the cases in which the data were not normal, nonparametric tests were used. To study the impact of potential risk factors for rejection episode, logistic regression analysis was performed. Multivariable models were used to explore confounding risk factors where appropriate. A two-tailed probability, 5%, was considered statistically significant.\n\nResults\n\nOf the total eyes that had DMEK during the study period (excluding the 45 eyes with primary graft failure), 25 (2.54%, 25/981) eyes were diagnosed with allograft rejection. Fig. 1a and b shows representative images of graft rejection in two eyes. Table 1 shows the comparison of clinical and demographic parameters of the eyes with rejection (n = 25) and those without rejection (n = 98). Table 2 illustrates the clinical profile and outcomes of rejection episodes. The median age of patients was 53 (interquartile range, IQR, 45\u201362) years. Thirteen (52%) were females.\n\n(a and b) Representative images of graft rejection after DMEK. (a) Slit-lamp photograph showing perilimbal congestion, corneal edema with diffusely scattered large keratic precipitates (highlighted in inset) in a female patient with 20 days history of blurred vision. (b) Slit-lamp photograph showing diffuse corneal edema and conjunctival congestion in a male patient with 4 days history of blurred vision\n\nClinical characteristics and demographics of 25 eyes with rejection after DMEK (study group) versus 98 eyes without rejection (control group)\n\nParameters\tStudy group\tControl group\t \tAge, Median (IQR) (years)\t53 (45,62)\t65.5 (56.2, 70.8)\t \tGender \u00a0\u00a0Male \u00a0\u00a0Female\t 12 (48%) 13 (52%)\t 56 (57%) 42 (43%)\t \tRebubbling \u00a0\u00a0Yes \u00a0\u00a0No\t 8 (32%) 17 (68%)\t 7 (8%) 91 (93%)\t \tIndications of surgery \u00a0\u00a0Failed graft \u00a0\u00a0Failed PK \u00a0\u00a0Failed DSEK \u00a0\u00a0Endothelial Dystrophy \u00a0\u00a0Post-Cataract surgery edema \u00a0\u00a0Edema post-inflammation\t 11 (44%) 1 10 5 (20%) 7 (28%) 2 (8%)\t 14 (14%) 2 12 53 (54%) 22 (22%) 9 (9%)\t \tDonor Parameters \u00a0\u00a0Age of Donor (Median, IQR) \u00a0\u00a0Sex of Donor \u00a0\u00a0Male \u00a0\u00a0Female\t 60 (52,65) 17 (68%) 8 (32%)\t 60 (55,65) 66 (67%) 32 (33%)\t \tOcular Co-morbidities \u00a0\u00a0Peripheral Anterior Synechiae \u00a0\u00a0Glaucoma\t 7 (28%) 8 (32%)\t 32 (33%) 45 (46%)\n\nPK penetrating keratoplasty, DSEK endothelial keratoplasty\n\nClinical Profile and outcomes of 25 eyes with Rejection after DMEK\n\nParameters\tNumbers\t%\t \tTime frame of rejection episode from surgery \u00a0\u00a06-12 months \u00a0\u00a012-24 months \u00a0\u00a0Beyond 24 months\t 13 9 3\t 52 36 12\t \tDuration of symptoms prior to clinic visit \u00a0\u00a0<7 days \u00a0\u00a0>7 days\t 07 18\t 28 72\t \tClinical Presentation of Rejection \u00a0\u00a0Asymptomatic \u00a0\u00a0Pain and discomfort \u00a0\u00a0Photophobia \u00a0\u00a0Decreased vision \u00a0\u00a0Keratic precipitates \u00a0\u00a0Edema \u00a0\u00a0Khodadoust line\t 1 4 12 24 20 22 1\t\t \tUsing steroids prior to rejection episode \u00a0\u00a0Yes \u00a0\u00a0No\t 19 6\t 76 24\t \tOutcomes \u00a0\u00a0Clear graft \u00a0\u00a0Persistent graft edema/Failure\t 17 8\t 68 32\t \tEndothelial cell loss at 1 year post rejection \u00a0\u00a0Mean ECL (%) (in eyes that recovered, n=14)\t 1786\t 72\n\nThe indications for DMEK in eyes with rejection were failed previous graft in 11 (44%) eyes, post-cataract surgery corneal edema in seven (28%) eyes, endothelial dystrophy in five (20%) eyes, and corneal edema postinflammatory condition (viral endothelitis and iridocorneal endothelial syndrome) in two (8%) eyes. Among the 11 failed grafts, 10 had failed after prior DSEK and one after prior penetrating keratoplasty (PK), and in sequential order, DMEK was the second graft in eight eyes and third graft in three eyes. Of the 11 failed previous grafts, eight (7 DSEK and one PK) had failed following graft rejection and other three were non-rejection graft failures. The baseline diagnosis in 11 eyes with failed grafts was post-cataract surgery corneal edema in six eyes, adherent leucoma in three eyes, and corneal ectasia in two eyes.\n\nThe majority of 24 (96%) patients were symptomatic at the clinic visit, and one patient was diagnosed incidentally during the clinic visit. The symptoms reported were decreased vision in 24 eyes, redness with pain/discomfort in four, and photophobia in 12 eyes. The mean duration of symptoms was 11 (range 7\u201314) days. The slit-lamp evaluation revealed diffuse cornea edema in 22 eyes, keratic precipitates in 20 eyes, anterior chamber reaction in 12 eyes, and Khodadoust line in one eye.\n\nAt the time of diagnosis of rejection, 19 (76%) eyes were using topical steroids in a dosage of 1\u20132 times a day; the remaining 6 (24%) eyes were not on steroid medications. Eight (32%) eyes had comorbidities that included secondary glaucoma in eight eyes, and seven eyes had peripheral anterior synechiae. Two out of 25 (8%) eyes had a history of rejection episode within 1 month of COVID-19 vaccine.\n\nThe median time of rejection episode from the surgery was 1 year (IQR 0.6, 1.3). Rejection episode occurred within 1 year after surgery in 13 (52%) eyes, between 1 and 2 years in 9 (36%) eyes, and three (12%) eyes had rejection beyond 2 years. The majority, 24 (96%) eyes, had one episode of rejection, and one eye had another second episode of rejection.\n\nAll eyes received intensive topical steroids; 2 (8%) patients additionally received one dose of IV methylprednisolone at the initial presentation. Of the 25 eyes, 17 (68%) eyes had improvement in graft clarity; the remaining 8 (32%) eyes failed to recover following the episode of rejection. Of the 17 eyes with complete recovery after rejection episode, 7 (41.1%) remained clear till the last follow-up. The mean endothelial cell loss (ECL) after rejection episode resolved was 1786 (1530\u20132019) cells/mm2, 72.5% compared to ECD documented at the clinic visit prior to rejection episode (n = 14 eyes). The median survival of the graft after episode of rejection was 1.1 (IQR 0.6\u20131.5) years. The mean duration of follow-up from the time of surgery was 2.56 (range 2\u20138) years in 25 eyes.\n\nIn the control group of without rejection episode, the median age was 65.5 (IQR 56.2\u201370.8) years. Fifty-six (57%) were males. The most common indication for DMEK was endothelial dystrophy in 53 (54) eyes, followed by post-cataract surgery corneal edema in 22 (22.4%) eyes, failed graft in 14 eyes (12 eyes with failed DSEK and two eyes with failed PK), and corneal edema postinflammatory etiology in 9 (9.2%) eyes. Ninety-three (96%) were on topical steroids at a dosage of 1\u20132 times daily till the last follow-up. The median survival time of the grafts in the control group was 5 (IQR 4\u20135.9) years.\n\nTable 3 shows the comparative analysis of various parameters in 25 eyes (study group) with 98 eyes of DMEK without rejection episode (control group). Younger age, rebubbling, nonusage of topical steroids, failed prior graft, and corneal edema post-cataract surgery were identified as significant risk factors for graft rejection in univariate analysis. In the multivariate analysis, surgery at a younger age, male gender, rebubbling, cessation of topical steroids and indication of DMEK comprising failed graft, corneal edema post cataract surgery, and corneal edema due to inflammatory causes emerged as significant risk factors for graft rejection.\n\nAnalysis of parameters identified as potential risk factors in the 25 eyes with rejection versus 98 eyes without rejection\n\nParameters assessed as potential risk factors\tUnivariate analysis\tMultivariate analysis\t \t\t \tHR (95%CI)\tP\tAdjusted HR (95%CI)\tP\t \tPatient\u2019s Age\t0.96 (0.94,0.99)\t0.002\t0.96 (0.93,0.99)\t0.006\t \tRecipient Gender \u00a0\u00a0(Male gender vs Female)\t 0.67 (0.31,1.47)\t 0.321\t 0.38 (0.14,1.01)\t 0.053\t \tRebubbling\t4.08 (1.76,9.48)\t0.001\t4.99 (1.63,15.29)\t0.005\t \tIndication of Surgery\t\t\t\t\t \t\u00a0\u00a0Post cataract surgery corneal edema \u00a0\u00a0Failed graft \u00a0\u00a0Corneal edema post inflammatory etiology\t2.84 (0.9,8.95)\t0.075\t5.57 (1.1,28.15)\t0.038\t \t5.58 (1.94,16.09)\t0.001\t20.66 (5.34,79.94)\t<0.001\t \t2.09 (0.41,10.79)\t0.377\t18.532 (5.59,33.33)\t0.049\t \tNonusage of steroids\t5 (2,12.5)\t< 0.001\t8.33 (2.08,33.33)\t0.003\t \tDonor gender (Male vs Female)\t0.98 (0.42,2.28)\t0.968\t1.13 (0.46,3.13)\t0.812\t \tDonor age\t0.97 (0.95,1)\t0.048\t0.994 (0.965,1.024)\t0.693\t \tPresence of Peripheral Anterior Synechiae\t1.219 (0.5,2.94)\t0.661\t2.04 (0.66,6.25)\t0.214\t \tGlaucoma\t1.75 (0.75,4)\t0.192\t3.57 (1.14,11.11)\t0.068\n\nOut of total 123 patients (study and control group together), 25 patients had COVID-19 vaccination. Of the 25 patients with vaccination, two (8%) patients had rejection within 1 month of vaccination, another two (8%) had rejection beyond 6 months after vaccination, and the large majority 21/25 (84%) patients had no remarkable event following vaccination. There did not seem to be any significant temporal relationship (clinically defined as 4\u20136 weeks following vaccination) of graft rejection with COVID-19 vaccination (8% vs 92%).\n\nThe logistic regression analysis model showed that none of the variables were significant risk factors for graft failure after rejection [Table 4].\n\nAnalysis of risk factors for graft failure after rejection episode\n\nParameters\tUnivariate Analysis\tMultivariate Analysis\t \t\t \tCrude HR (95%CI)\tCrude P\tAdjusted HR (95%CI)\tP\t \tRecipient Age\t1.03 (0.97,1.08)\t0.309\t1.07 (0.91,1.25)\t0.414\t \tGender: \u00a0\u00a0Male vs Female\t 1.26 (0.31,5.05)\t 0.744\t 2.63 (0.14,50.82)\t 0.522\t \tConcomitant Surgical Procedure\t1.11 (0.22,5.55)\t0.895\t0.62 (0.01,75.77)\t0.848\t \tGlaucoma\t0.53 (0.12,2.23)\t0.385\t0.02 (0,6.42)\t0.189\t \tRebubbling\t1.13 (0.23,5.6)\t0.882\t1.27 (0.06,28.75)\t0.881\t \tDuration of Rejection\t1.0075 (0.9891,1.0262)\t0.427\t0.9905 (0.9506,1.032)\t0.648\t \tNonuse of steroids at presentation\t2.39 (0.57,10.04)\t0.236\t14.94 (0.07,3137.52)\t0.322\t \tDonor ECD\t1.0021 (0.9981,1.006)\t0.304\t1.0039 (0.993,1.015)\t0.482\t \tDonor Age\t1.01 (0.93,1.1)\t0.809\t1.25 (0.8,1.95)\t0.331\n\nKaplan\u2013Meier (KM) survival curve [Fig. 2] describes the cumulative success probability of DMEK over the follow-up period. The probability of graft survival was 89.7% at 1 year, 81.9 at 2 years, 80% at 3 years, 79.9% at 4 years, and 77.9% at 5\u20138 years. There is a noticeable higher probability of graft rejection leading to failure in the initial period up to 2 years. KM plot also illustrates that after this initial period, the success rate remained relatively stable, with no additional failure up to 8 years. Fig. 3 shows the cumulative graft success probability after the graft rejection episode. The 6\u201312 months probability of graft survival after rejection episode was 70.8%, and 65% at 1\u20133 years after graft rejection episode.\n\nKaplan\u2013Meier survival curve showing probability of survival following graft rejection after DMEK\n\nKaplan\u2013Meier survival curve showing the graft survival after rejection episode\n\nDiscussion\n\nMost studies have consistently indicated a lower risk of rejection in DMEK compared to PK and DSEK. Although the exact reasons for the low risk of rejection remain unclear, it is most likely due to lesser antigenic load in DMEK. We found that the risk of rejection was 2.54% within a mean follow-up duration of 2.6 (range 2\u20138) years, which is comparable to the previous studies.\n\nThe clinical presentation of DMEK graft rejection is diverse. The common symptoms reported are pain, discomfort, photophobia, and a decrease in vision, but asymptomatic nature with incidental diagnosis at clinic visits has been well documented. The various signs that have been noted in the clinic visits include congestion, anterior chamber reaction, keratic precipitates, and edema. Dapena et al. reported one patient of DMEK graft rejection who had a rejection line. Hos et al. reported that most of the patients with DMEK graft rejection were clinically asymptomatic at presentation and were diagnosed on a routine clinical visit. In our study, all except one were symptomatic and complained of reduced vision at presentation. The most common clinical feature was corneal edema, followed by keratic precipitates and Khodadoust line.\n\nIn view of lower risk of rejection in DMEK, one clinical question is when the topical steroids can be discontinued after surgery. Price et al. studied incidence of rejection after discontinuing topical steroids and found it to be as high as 6% in the group that discontinued topical steroids within 1 year of DMEK. Hos et al. reported that the probability of graft rejection was the highest in the first 2 years (3.2%) after DMEK and slightly less thereafter for the next 2 years (2.3%). We observed that most (22/25 eyes) of the rejections occurred within the first 2 years after surgery. These observations coupled with asymptomatic or often subtle initial symptoms of graft rejection in DMEK in many eyes underscore the importance of topical steroid therapy up to 2 years and beyond after the surgery.\n\nAlthough the risk of rejection in DMEK is lower than that in PK and DSEK, several situations may be associated with an increased risk. In this study, we analyzed some of the risk factors for rejection after DMEK and compared these with the control eyes that had minimum follow-up of 2 years and did not have rejection episode. We found that the risk of graft rejection was significantly higher in failed prior grafts, post-cataract surgery corneal edema, and eyes with inflammatory causes of corneal edema. The other significant risk factors identified were younger age, rebubbling, and nonuse of steroids at presentation. Younger recipient age has been a well-recognized risk factor for rejection after keratoplasty. Rebubbling as a risk factor could be indirectly explained because of another intervention after primary surgery leading to additional inflammation and increased immunological activity. Glaucoma has been reported to be an important risk factor for both immunological graft rejection and nonimmunogenic graft failure in penetrating keratoplasty and endothelial keratoplasty. Anshu et al. identified that the alteration in the proteomic composition of aqueous humor could be a cause for increased endothelial cell attrition and poor graft survival in post-glaucoma drainage eyes. Our study did not show glaucoma as a strong risk factor for graft rejection. Glaucoma as a risk factor for graft rejection is a complex parameter for assessment. The eyes with coexisting glaucoma also have a higher chance of nonimmunogenic graft failure, which might precede or overlap with allograft rejection episodes. Although we could not analyze the absolute numbers of nonimmunogenic graft failures in glaucoma eyes during the study period, this information would be analyzed in future studies. Post COVID-19 pandemic, there were several reports of graft rejection after DMEK during active infection and associated with COVID-19 vaccination. We did not find any significant temporal association with COVID-19 vaccination in our study.\n\nThe majority (17/25 eyes, 68%) of grafts recovered after the rejection episode; however, only 7/17 (41.1%) eyes remained clear till the last follow-up. The mean endothelial cell loss at 6\u201312 months after rejection was 73% in comparison to the study by Hos et al., which reported that the ECL post rejection was 50% and 53% at 3 months and 1 year follow-up. The higher ECL in our study could be due to differences in the indications of surgery, and severity of the rejection episodes. Additionally, most cases of rejection in the latter study were in FECD, while the indications were heterogeneous in our study. Higher ECL after the rejection episode may be the reason for decreased survival of the grafts post recovery of the rejection in our study.\n\nOn comparing with our previous study, where we analyzed the graft rejection and the risk factors of rejection after DSEK, we found that similar indications (failed prior graft and corneal edema postinflammatory cause) and the nonuse of steroids were the risk factors common to both DSEK and DMEK. The risk of graft rejection was 3.6% after DSEK, in comparison to 2.54% in this study. We noted that the 6\u201312 months graft survival rate following rejection after DSEK was higher than DMEK (90% vs 70.8%). A possible reason could be the higher ECL postrejection in DMEK versus DSEK in the previous study (73% vs 55%).\n\nOne of the limitations of the study is that we could not compare with the entire cohort of eyes that underwent DMEK during the study period. Even though the control group included the 98 eyes without rejection, they had a minimum follow-up of 2 years, which is the most sensitive time frame of rejection after DMEK, making the comparative analysis of risk factors insightful.\n\nIn the current literature, there is a lack of prospective randomized study after DMEK with a defined topical steroid application regime, follow-up scheme documenting endothelial cell loss, and the frequency of asymptomatic graft rejections after DMEK. Additionally, the influence of HLA incompatibility in DMEK is unclear. Future studies may be planned prospectively specifically to address these parameters as risk factors for graft rejection after DMEK.\n\nConclusion\n\nThe study highlights the important risk factors associated with rejection after DMEK. Based on an institutional practice set up with electron medical record systems, it represents the real-world data and a comprehensive analysis of graft rejections after DMEK.\n\nContributor statement\n\nData collection, initial writing of the draft- SS; Statistical analysis- HA; Concept, writing, editing and critical analysis- SCH\n\nConflicts of interest:\n\nThere are no conflicts of interest.\n\nReferences\n\nCost-effectiveness analysis of descemet\u2019s membrane endothelial keratoplasty versus descemet\u2019s stripping endothelial keratoplasty in the United States\n\nLong-term outcome of descemet membrane endothelial keratoplasty in eyes with Fuchs endothelial corneal dystrophy versus pseudophakic bullous keratopathy\n\nGraft survival and clinical outcomes of Descemet membrane endothelial keratoplasty: Long-term results\n\nDescemet membrane endothelial keratoplasty (DMEK): An update on safety, efficacy and patient selection\n\nRecent indications of endothelial keratoplasty at a tertiary eye care center in South India\n\nCorneal endothelial transplantation\n\nRisk factors for descemet membrane endothelial keratoplasty rejection: Current perspectives- Systematic review\n\nDescemet membrane endothelial keratoplasty: safety and outcomes: A Report by the American Academy of Ophthalmology\n\nTen-year outcomes after DMEK, DSAEK, and PK: Insights on graft survival, endothelial cell density loss, rejection and visual acuity\n\nRisk of corneal transplant rejection significantly reduced with Descemet\u2019s membrane endothelial keratoplasty\n\nIncidence and clinical course of immune reactions after Descemet membrane endothelial keratoplasty: Retrospective analysis of 1000 consecutive eyes\n\nFive-year graft survival and clinical outcomes of 500 consecutive cases after descemet membrane endothelial keratoplasty\n\nOverall clinical outcomes of Descemet membrane endothelial keratoplasty in 600 consecutive eyes: A large retrospective case series\n\nDescemet\u2019s membrane endothelial keratoplasty: Risk of immunologic rejection episodes after discontinuing topical corticosteroids\n\nIncidence of early allograft rejection after Descemet membrane endothelial keratoplasty\n\nFactors associated with graft rejection in the cornea preservation time study\n\nAlterations in the aqueous humor proteome in patients with a glaucoma shunt device\n\nClinical characteristics, risk factor analysis and outcomes in 61 eyes with graft rejection after descemet stripping endothelial keratoplasty, with a review of literature",
  "pmc_id": "PMC12707381",
  "doi": "10.4103/IJO.IJO_722_25",
  "pubmed_url": "https://pubmed.ncbi.nlm.nih.gov/41288624/"
}